<?xml version="1.0" encoding="UTF-8"?>
<musicdata>
<music title="エンジョイ・シンプル・イングリッシュ" hdate="8月3日放送分" kouza="エンジョイ・シンプル・イングリッシュ" code="3502686" file="20-ese-3502-686.mp4" nendo="2020" pgcode="H1"></music>
<music title="エンジョイ・シンプル・イングリッシュ" hdate="8月4日放送分" kouza="エンジョイ・シンプル・イングリッシュ" code="3502687" file="20-ese-3502-687.mp4" nendo="2020" pgcode="H1"></music>
<music title="エンジョイ・シンプル・イングリッシュ" hdate="8月5日放送分" kouza="エンジョイ・シンプル・イングリッシュ" code="3502688" file="20-ese-3502-688.mp4" nendo="2020" pgcode="H1"></music>
<music title="エンジョイ・シンプル・イングリッシュ" hdate="8月6日放送分" kouza="エンジョイ・シンプル・イングリッシュ" code="3502689" file="20-ese-3502-689.mp4" nendo="2020" pgcode="H1"></music>
<music title="エンジョイ・シンプル・イングリッシュ" hdate="8月7日放送分" kouza="エンジョイ・シンプル・イングリッシュ" code="3502690" file="20-ese-3502-690.mp4" nendo="2020" pgcode="H1"></music>
</musicdata>
