<?xml version="1.0" encoding="UTF-8"?>
<musicdata>
<music title="ラジオビジネス英語" hdate="12月5日放送分" kouza="ラジオビジネス英語" code="4232166" file="22-ebn-4232-166" dir="" nendo="2022" pgcode="H2"></music>
<music title="ラジオビジネス英語" hdate="12月6日放送分" kouza="ラジオビジネス英語" code="4232167" file="22-ebn-4232-167" dir="" nendo="2022" pgcode="H2"></music>
<music title="ラジオビジネス英語" hdate="12月7日放送分" kouza="ラジオビジネス英語" code="4232168" file="22-ebn-4232-168" dir="" nendo="2022" pgcode="H2"></music>
<music title="ラジオビジネス英語" hdate="12月8日放送分" kouza="ラジオビジネス英語" code="4232169" file="22-ebn-4232-169" dir="" nendo="2022" pgcode="H2"></music>
<music title="ラジオビジネス英語" hdate="12月9日放送分" kouza="ラジオビジネス英語" code="4232170" file="22-ebn-4232-170" dir="" nendo="2022" pgcode="H2"></music>
</musicdata>
