<?xml version="1.0" encoding="UTF-8"?>
<musicdata>
<music title="ラジオビジネス英語" hdate="9月13日放送分" kouza="ラジオビジネス英語" code="4232111" file="21-ebn-4232-111.mp4" nendo="2021" pgcode="H1"></music>
<music title="ラジオビジネス英語" hdate="9月14日放送分" kouza="ラジオビジネス英語" code="4232112" file="21-ebn-4232-112.mp4" nendo="2021" pgcode="H1"></music>
<music title="ラジオビジネス英語" hdate="9月15日放送分" kouza="ラジオビジネス英語" code="4232113" file="21-ebn-4232-113.mp4" nendo="2021" pgcode="H1"></music>
<music title="ラジオビジネス英語" hdate="9月16日放送分" kouza="ラジオビジネス英語" code="4232114" file="21-ebn-4232-114.mp4" nendo="2021" pgcode="H1"></music>
<music title="ラジオビジネス英語" hdate="9月17日放送分" kouza="ラジオビジネス英語" code="4232115" file="21-ebn-4232-115.mp4" nendo="2021" pgcode="H1"></music>
</musicdata>
