<?xml version="1.0" encoding="UTF-8"?>
<musicdata>
<music title="まいにちハングル講座" hdate="2月21日放送分" kouza="まいにちハングル講座" code="4246816" file="21-kor-4246-816.mp4" nendo="2021" pgcode="H2"></music>
<music title="まいにちハングル講座" hdate="2月22日放送分" kouza="まいにちハングル講座" code="4246817" file="21-kor-4246-817.mp4" nendo="2021" pgcode="H2"></music>
<music title="まいにちハングル講座" hdate="2月23日放送分" kouza="まいにちハングル講座" code="4246818" file="21-kor-4246-818.mp4" nendo="2021" pgcode="H2"></music>
<music title="まいにちハングル講座" hdate="2月24日放送分" kouza="まいにちハングル講座" code="4246819" file="21-kor-4246-819.mp4" nendo="2021" pgcode="H2"></music>
<music title="まいにちハングル講座" hdate="2月25日放送分" kouza="まいにちハングル講座" code="4246820" file="21-kor-4246-820.mp4" nendo="2021" pgcode="H2"></music>
</musicdata>
