<?xml version="1.0" encoding="UTF-8"?>
<musicdata>
<music title="まいにちハングル講座" hdate="8月30日放送分" kouza="まいにちハングル講座" code="4246101" file="21-kor-4246-101.mp4" nendo="2021" pgcode="H1"></music>
<music title="まいにちハングル講座" hdate="8月31日放送分" kouza="まいにちハングル講座" code="4246102" file="21-kor-4246-102.mp4" nendo="2021" pgcode="H1"></music>
<music title="まいにちハングル講座" hdate="9月1日放送分" kouza="まいにちハングル講座" code="4246103" file="21-kor-4246-103.mp4" nendo="2021" pgcode="H1"></music>
<music title="まいにちハングル講座" hdate="9月2日放送分" kouza="まいにちハングル講座" code="4246104" file="21-kor-4246-104.mp4" nendo="2021" pgcode="H1"></music>
<music title="まいにちハングル講座" hdate="9月3日放送分" kouza="まいにちハングル講座" code="4246105" file="21-kor-4246-105.mp4" nendo="2021" pgcode="H1"></music>
</musicdata>
