<?xml version="1.0" encoding="UTF-8"?>
<musicdata>
<music title="ラジオ英会話" hdate="9月19日放送分" kouza="ラジオ英会話" code="4235491" file="22-er-4235-491.mp4" nendo="2022" pgcode="F0"></music>
<music title="ラジオ英会話" hdate="9月20日放送分" kouza="ラジオ英会話" code="4235492" file="22-er-4235-492.mp4" nendo="2022" pgcode="F0"></music>
<music title="ラジオ英会話" hdate="9月21日放送分" kouza="ラジオ英会話" code="4235493" file="22-er-4235-493.mp4" nendo="2022" pgcode="F0"></music>
<music title="ラジオ英会話" hdate="9月22日放送分" kouza="ラジオ英会話" code="4235494" file="22-er-4235-494.mp4" nendo="2022" pgcode="F0"></music>
<music title="ラジオ英会話" hdate="9月23日放送分" kouza="ラジオ英会話" code="4235495" file="22-er-4235-495.mp4" nendo="2022" pgcode="F0"></music>
</musicdata>
