<?xml version="1.0" encoding="UTF-8"?>
<musicdata>
<music title="中学生の基礎英語【レベル1】" hdate="6月7日放送分" kouza="中学生の基礎英語【レベル1】" code="4252836" file="21-ek1-4252-836.mp4" nendo="2021" pgcode="F0"></music>
<music title="中学生の基礎英語【レベル1】" hdate="6月8日放送分" kouza="中学生の基礎英語【レベル1】" code="4252837" file="21-ek1-4252-837-re01.mp4" nendo="2021" pgcode="F0"></music>
<music title="中学生の基礎英語【レベル1】" hdate="6月9日放送分" kouza="中学生の基礎英語【レベル1】" code="4252838" file="21-ek1-4252-838.mp4" nendo="2021" pgcode="F0"></music>
<music title="中学生の基礎英語【レベル1】" hdate="6月10日放送分" kouza="中学生の基礎英語【レベル1】" code="4252839" file="21-ek1-4252-839.mp4" nendo="2021" pgcode="F0"></music>
<music title="中学生の基礎英語【レベル1】" hdate="6月11日放送分" kouza="中学生の基礎英語【レベル1】" code="4252840" file="21-ek1-4252-840.mp4" nendo="2021" pgcode="F0"></music>
</musicdata>
