<?xml version="1.0" encoding="UTF-8"?>
<musicdata>
<music title="基礎英語3" hdate="10月26日放送分" kouza="基礎英語3" code="4236084" file="20-ek3-4236-084.mp4" nendo="2020" pgcode="F0"></music>
<music title="基礎英語3" hdate="10月27日放送分" kouza="基礎英語3" code="4236085" file="20-ek3-4236-085.mp4" nendo="2020" pgcode="F0"></music>
<music title="基礎英語3" hdate="10月28日放送分" kouza="基礎英語3" code="4236086" file="20-ek3-4236-086.mp4" nendo="2020" pgcode="F0"></music>
<music title="基礎英語3" hdate="10月29日放送分" kouza="基礎英語3" code="4236087" file="20-ek3-4236-087.mp4" nendo="2020" pgcode="F0"></music>
<music title="基礎英語3" hdate="10月30日放送分" kouza="基礎英語3" code="4236088" file="20-ek3-4236-088.mp4" nendo="2020" pgcode="F0"></music>
</musicdata>
