<?xml version="1.0" encoding="UTF-8"?>
<musicdata>
<music title="まいにち中国語" hdate="10月21日放送分" kouza="まいにち中国語" code="4243616" file="19-chi-4243-616.mp4" nendo="2019" pgcode="F0"></music>
<music title="まいにち中国語" hdate="10月22日放送分" kouza="まいにち中国語" code="4243617" file="19-chi-4243-617.mp4" nendo="2019" pgcode="F0"></music>
<music title="まいにち中国語" hdate="10月23日放送分" kouza="まいにち中国語" code="4243618" file="19-chi-4243-618.mp4" nendo="2019" pgcode="F0"></music>
<music title="まいにち中国語" hdate="10月24日放送分" kouza="まいにち中国語" code="4243619" file="19-chi-4243-619.mp4" nendo="2019" pgcode="F0"></music>
<music title="まいにち中国語" hdate="10月25日放送分" kouza="まいにち中国語" code="4243620" file="19-chi-4243-620.mp4" nendo="2019" pgcode="F0"></music>
</musicdata>
