<?xml version="1.0" encoding="UTF-8"?>
<musicdata>
<music title="英会話タイムトライアル" hdate="1月31日放送分" kouza="英会話タイムトライアル" code="4237173" file="21-ett-4237-173.mp4" nendo="2021" pgcode="F0"></music>
<music title="英会話タイムトライアル" hdate="2月1日放送分" kouza="英会話タイムトライアル" code="4237174" file="21-ett-4237-174.mp4" nendo="2021" pgcode="F0"></music>
<music title="英会話タイムトライアル" hdate="2月2日放送分" kouza="英会話タイムトライアル" code="4237175" file="21-ett-4237-175.mp4" nendo="2021" pgcode="F0"></music>
<music title="英会話タイムトライアル" hdate="2月3日放送分" kouza="英会話タイムトライアル" code="4237176" file="21-ett-4237-176.mp4" nendo="2021" pgcode="F0"></music>
<music title="英会話タイムトライアル" hdate="2月4日放送分" kouza="英会話タイムトライアル" code="4237177" file="21-ett-4237-177.mp4" nendo="2021" pgcode="F0"></music>
</musicdata>
