<?xml version="1.0" encoding="UTF-8"?>
<musicdata>
<music title="英会話タイムトライアル" hdate="10月11日放送分" kouza="英会話タイムトライアル" code="4237118" file="21-ett-4237-118.mp4" nendo="2021" pgcode="F0"></music>
<music title="英会話タイムトライアル" hdate="10月12日放送分" kouza="英会話タイムトライアル" code="4237119" file="21-ett-4237-119.mp4" nendo="2021" pgcode="F0"></music>
<music title="英会話タイムトライアル" hdate="10月13日放送分" kouza="英会話タイムトライアル" code="4237120" file="21-ett-4237-120.mp4" nendo="2021" pgcode="F0"></music>
<music title="英会話タイムトライアル" hdate="10月14日放送分" kouza="英会話タイムトライアル" code="4237121" file="21-ett-4237-121.mp4" nendo="2021" pgcode="F0"></music>
<music title="英会話タイムトライアル" hdate="10月15日放送分" kouza="英会話タイムトライアル" code="4237122" file="21-ett-4237-122.mp4" nendo="2021" pgcode="F0"></music>
</musicdata>
