<?xml version="1.0" encoding="UTF-8"?>
<musicdata>
<music title="英会話タイムトライアル" hdate="11月9日放送分" kouza="英会話タイムトライアル" code="4237927" file="20-ett-4237-927.mp4" nendo="2020" pgcode="F0"></music>
<music title="英会話タイムトライアル" hdate="11月10日放送分" kouza="英会話タイムトライアル" code="4237928" file="20-ett-4237-928.mp4" nendo="2020" pgcode="F0"></music>
<music title="英会話タイムトライアル" hdate="11月11日放送分" kouza="英会話タイムトライアル" code="4237929" file="20-ett-4237-929.mp4" nendo="2020" pgcode="F0"></music>
<music title="英会話タイムトライアル" hdate="11月12日放送分" kouza="英会話タイムトライアル" code="4237930" file="20-ett-4237-930.mp4" nendo="2020" pgcode="F0"></music>
<music title="英会話タイムトライアル" hdate="11月13日放送分" kouza="英会話タイムトライアル" code="4237931" file="20-ett-4237-931.mp4" nendo="2020" pgcode="F0"></music>
</musicdata>
