<?xml version="1.0" encoding="UTF-8"?>
<musicdata>
<music title="英会話タイムトライアル" hdate="3月15日放送分" kouza="英会話タイムトライアル" code="4237003" file="20-ett-4237-003.mp4" nendo="2020" pgcode="F0"></music>
<music title="英会話タイムトライアル" hdate="3月16日放送分" kouza="英会話タイムトライアル" code="4237004" file="20-ett-4237-004.mp4" nendo="2020" pgcode="F0"></music>
<music title="英会話タイムトライアル" hdate="3月17日放送分" kouza="英会話タイムトライアル" code="4237005" file="20-ett-4237-005.mp4" nendo="2020" pgcode="F0"></music>
<music title="英会話タイムトライアル" hdate="3月18日放送分" kouza="英会話タイムトライアル" code="4237006" file="20-ett-4237-006.mp4" nendo="2020" pgcode="F0"></music>
<music title="英会話タイムトライアル" hdate="3月19日放送分" kouza="英会話タイムトライアル" code="4237007" file="20-ett-4237-007.mp4" nendo="2020" pgcode="F0"></music>
</musicdata>
